{
    "q_learning_vec": [],
    "opt_mixed_vec": [
        42723.95,
        51347.175,
        53292.325
    ],
    "opt_fixed_vec": [
        42717.67,
        51351.115,
        44165.195
    ],
    "degree_cutoff_vec": [
        44433.97,
        57603.7625,
        63922.92
    ],
    "param_vec": [
        0.2,
        0.5,
        1
    ],
    "baseline_profit_vec": [
        28235.32,
        31752.62,
        37517.67
    ],
    "influence_cutoff_vec": [
        28302.8,
        31819.895,
        37510.24
    ],
    "time_cutoff_vec": [
        41512.7525,
        50230.28,
        57748.405
    ],
    "boosted_cutoff_vec": [
        28231.125,
        31771.025,
        37387.225
    ]
}